rozental_as_a_service/__init__.py
rozental_as_a_service/args_utils.py
rozental_as_a_service/ast_utils.py
rozental_as_a_service/common_types.py
rozental_as_a_service/config.py
rozental_as_a_service/config_utils.py
rozental_as_a_service/db_utils.py
rozental_as_a_service/extractors_utils.py
rozental_as_a_service/files_utils.py
rozental_as_a_service/list_utils.py
rozental_as_a_service/logging_urils.py
rozental_as_a_service/obscene_utils.py
rozental_as_a_service/rozental.py
rozental_as_a_service/strings_extractors.py
rozental_as_a_service/text_utils.py
rozental_as_a_service/typos_backends.py
rozental_as_a_service/data/__init__.py
rozental_as_a_service/data/en.tar.gz
rozental_as_a_service/data/prepare_word_count.py
rozental_as_a_service/data/ru.tar.gz
rozental_as_a_service-1.2.2.dist-info/LICENSE
rozental_as_a_service-1.2.2.dist-info/METADATA
rozental_as_a_service-1.2.2.dist-info/WHEEL
rozental_as_a_service-1.2.2.dist-info/entry_points.txt
rozental_as_a_service-1.2.2.dist-info/top_level.txt
rozental_as_a_service-1.2.2.dist-info/RECORD
