Metadata-Version: 2.1
Name: rozental-as-a-service
Version: 1.2.2
Summary: Package to find typos in russian text.
Home-page: https://github.com/Melevir/rozental_as_a_service
Author: Ilya Lebedev
Author-email: melevir@gmail.com
License: MIT
Keywords: typos
Platform: UNKNOWN
Classifier: Environment :: Console
Classifier: Operating System :: OS Independent
Classifier: Topic :: Software Development :: Libraries :: Python Modules
Classifier: Topic :: Software Development :: Quality Assurance
Classifier: Programming Language :: Python
Classifier: Programming Language :: Python :: 3.7
Classifier: Programming Language :: Python :: 3.8
Classifier: Programming Language :: Python :: 3.9
License-File: LICENSE
Requires-Dist: setuptools
Requires-Dist: tabulate (>=0.8)
Requires-Dist: requests (>=2.22.0)
Requires-Dist: Markdown (>=3.1.1)
Requires-Dist: beautifulsoup4 (>=4.8.0)
Requires-Dist: esprima (==4.0.1)
Requires-Dist: mypy-extensions (>=0.4.1)
Requires-Dist: sentry-sdk (>=0.14.3)
Requires-Dist: chardet
Requires-Dist: autocorrect
